clovers_setu_collection/__init__.py
clovers_setu_collection/api/__init__.py
clovers_setu_collection/api/Anosu.py
clovers_setu_collection/api/interface.py
clovers_setu_collection/api/Lolicon.py
clovers_setu_collection/api/MirlKoi.py
clovers_setu_collection/config.py
clovers_setu_collection-0.2.3.post1.dist-info/LICENSE
clovers_setu_collection-0.2.3.post1.dist-info/METADATA
clovers_setu_collection-0.2.3.post1.dist-info/WHEEL
clovers_setu_collection-0.2.3.post1.dist-info/RECORD
